rosbag_topic_compare/__init__.py
rosbag_topic_compare/__main__.py
rosbag_topic_compare/topic_comparator.py
rosbag_topic_compare/utils.py
rosbag_topic_compare-0.0.3.dist-info/entry_points.txt
rosbag_topic_compare-0.0.3.dist-info/LICENSE
rosbag_topic_compare-0.0.3.dist-info/WHEEL
rosbag_topic_compare-0.0.3.dist-info/METADATA
rosbag_topic_compare-0.0.3.dist-info/RECORD
