Metadata-Version: 2.1
Name: rosbag-topic-compare
Version: 0.0.3
Summary: Compare topics between rosbags in a folder
Author-email: damienlarocque <phicoltan@gmail.com>
Requires-Python: >=3.9
Classifier: License :: OSI Approved :: MIT License
Classifier: Programming Language :: Python :: 3
Classifier: Programming Language :: Python :: 3.9
Requires-Dist: pyyaml
Requires-Dist: rosbags
Requires-Dist: tqdm
Requires-Dist: black ; extra == "dev"
Requires-Dist: pylint ; extra == "dev"
Requires-Dist: bump2version ; extra == "dev"
Requires-Dist: matplotlib ; extra == "plot"
Project-URL: Homepage, https://github.com/IamPhytan/rosbag-topic-compare
Project-URL: Repository on GitHub, https://github.com/IamPhytan/rosbag-topic-compare
Project-URL: Repository on GitLab, https://gitlab.com/damienlarocque/rosbag-topic-compare
Provides-Extra: dev
Provides-Extra: plot
